Dshell/__init__.py
Dshell/full_import.py
Dshell/DISCORD_COMMANDS/__init__.py
Dshell/DISCORD_COMMANDS/dshell_channel.py
Dshell/DISCORD_COMMANDS/dshell_embed.py
Dshell/DISCORD_COMMANDS/dshell_interaction.py
Dshell/DISCORD_COMMANDS/dshell_member.py
Dshell/DISCORD_COMMANDS/dshell_message.py
Dshell/DISCORD_COMMANDS/dshell_pastbin.py
Dshell/DISCORD_COMMANDS/dshell_role.py
Dshell/DISCORD_COMMANDS/dshell_ui.py
Dshell/DISCORD_COMMANDS/utils/__init__.py
Dshell/DISCORD_COMMANDS/utils/utils_global.py
Dshell/DISCORD_COMMANDS/utils/utils_list.py
Dshell/DISCORD_COMMANDS/utils/utils_member.py
Dshell/DISCORD_COMMANDS/utils/utils_message.py
Dshell/DISCORD_COMMANDS/utils/utils_permissions.py
Dshell/DISCORD_COMMANDS/utils/utils_string.py
Dshell/DISCORD_COMMANDS/utils/utils_thread.py
Dshell/_DshellInterpreteur/__init__.py
Dshell/_DshellInterpreteur/cached_messages.py
Dshell/_DshellInterpreteur/dshell_arguments.py
Dshell/_DshellInterpreteur/dshell_interpreter.py
Dshell/_DshellInterpreteur/dshell_scope.py
Dshell/_DshellInterpreteur/errors.py
Dshell/_DshellInterpreteur/utils_interpreter.py
Dshell/_DshellParser/__init__.py
Dshell/_DshellParser/ast_nodes.py
Dshell/_DshellParser/dshell_parser.py
Dshell/_DshellTokenizer/__init__.py
Dshell/_DshellTokenizer/dshell_keywords.py
Dshell/_DshellTokenizer/dshell_token_type.py
Dshell/_DshellTokenizer/dshell_tokenizer.py
dshellinterpreter-1.0.0.9.dist-info/licenses/LICENSE
dshellinterpreter-1.0.0.9.dist-info/METADATA
dshellinterpreter-1.0.0.9.dist-info/WHEEL
dshellinterpreter-1.0.0.9.dist-info/top_level.txt
dshellinterpreter-1.0.0.9.dist-info/RECORD
