Metadata-Version: 2.4
Name: dshellInterpreter
Version: 1.0.0.9
Summary: A Discord bot interpreter for creating custom commands and automations.
Home-page: https://github.com/BOXERRMD/Dshell_Interpreter
Author: Chronos
Author-email: vagabonwalybi@gmail.com
License: MIT
Project-URL: Bug Tracker, https://github.com/BOXERRMD/Dshell_Interpreter/issues
Project-URL: Source, https://github.com/BOXERRMD/Dshell_Interpreter
Keywords: discord bot interpreter automation commands
Classifier: Programming Language :: Python :: 3
Classifier: Operating System :: OS Independent
Requires-Python: >=3.9
License-File: LICENSE
Requires-Dist: py-cord==2.6.1
Requires-Dist: requests
Requires-Dist: pycordviews
Dynamic: author
Dynamic: author-email
Dynamic: classifier
Dynamic: description
Dynamic: description-content-type
Dynamic: home-page
Dynamic: keywords
Dynamic: license
Dynamic: license-file
Dynamic: project-url
Dynamic: requires-dist
Dynamic: requires-python
Dynamic: summary
